cpaas_test_python/__init__.py
cpaas_test_python/__version__.py
cpaas_test_python/config.py
cpaas_test_python/request_options.py
cpaas_test_python/utility.py
cpaas_test_python/exception/__init__.py
cpaas_test_python/exception/bad_request_exception.py
cpaas_test_python/exception/bulk_message_create_failed_exception.py
cpaas_test_python/exception/bulk_message_list_message_retry_limit_exceed_exception.py
cpaas_test_python/exception/bulk_message_show_retry_limit_exceed_exception.py
cpaas_test_python/exception/file_download_failed_exception.py
cpaas_test_python/exception/file_not_found_exception.py
cpaas_test_python/exception/file_upload_failed_exception.py
cpaas_test_python/exception/forbidden_exception.py
cpaas_test_python/exception/invalid_params_exception.py
cpaas_test_python/exception/invalid_request_options_exception.py
cpaas_test_python/exception/karaden_exception.py
cpaas_test_python/exception/not_found_exception.py
cpaas_test_python/exception/too_many_requests_exception.py
cpaas_test_python/exception/unauthorized_exception.py
cpaas_test_python/exception/unexpected_value_exception.py
cpaas_test_python/exception/unknown_error_exception.py
cpaas_test_python/exception/unprocessable_entity_exception.py
cpaas_test_python/model/__init__.py
cpaas_test_python/model/bulk_file.py
cpaas_test_python/model/bulk_message.py
cpaas_test_python/model/collection.py
cpaas_test_python/model/error.py
cpaas_test_python/model/error_interface.py
cpaas_test_python/model/karaden_object.py
cpaas_test_python/model/karaden_object_interface.py
cpaas_test_python/model/message.py
cpaas_test_python/model/requestable.py
cpaas_test_python/net/__init__.py
cpaas_test_python/net/requestor_interface.py
cpaas_test_python/net/requests_no_contents_response.py
cpaas_test_python/net/requests_requestor.py
cpaas_test_python/net/requests_response.py
cpaas_test_python/net/response_interface.py
cpaas_test_python/param/__init__.py
cpaas_test_python/param/message_cancel_params.py
cpaas_test_python-0.1.1.dist-info/licenses/LICENSE
cpaas_test_python-0.1.1.dist-info/METADATA
cpaas_test_python-0.1.1.dist-info/WHEEL
cpaas_test_python-0.1.1.dist-info/top_level.txt
cpaas_test_python-0.1.1.dist-info/RECORD
